[{"id":1,"first_name":"Irina","last_name":"Sisnett","email":"isisnett0@google.com.hk","date_of_birth":"12/27/2017","age":46,"country":"Russia","phone":"9076844239"},
{"id":2,"first_name":"Heda","last_name":"Gokes","email":"hgokes1@smh.com.au","date_of_birth":"7/16/1976","age":36,"country":"Vietnam","phone":"2059024353"},
{"id":3,"first_name":"Gabby","last_name":"Purchase","email":"gpurchase2@tripod.com","date_of_birth":"4/17/1981","age":33,"country":"China","phone":"7631057747"},
{"id":4,"first_name":"Xena","last_name":"Cansdall","email":"xcansdall3@dedecms.com","date_of_birth":"10/30/1978","age":23,"country":"China","phone":"8108951125"},
{"id":5,"first_name":"Matteo","last_name":"Peace","email":"mpeace4@instagram.com","date_of_birth":"11/17/2013","age":23,"country":"China","phone":"8735233569"},
{"id":6,"first_name":"Moore","last_name":"Bartel","email":"mbartel5@loc.gov","date_of_birth":"11/14/2004","age":18,"country":"Peru","phone":"1914397404"},
{"id":7,"first_name":"Timothy","last_name":"Wandtke","email":"twandtke6@mayoclinic.com","date_of_birth":"11/26/1976","age":46,"country":"Tunisia","phone":"9191003516"},
{"id":8,"first_name":"Arney","last_name":"Twells","email":"atwells7@businessinsider.com","date_of_birth":"12/27/2004","age":53,"country":"Russia","phone":"8133476652"},
{"id":9,"first_name":"Alfie","last_name":"Billes","email":"abilles8@php.net","date_of_birth":"12/29/2012","age":36,"country":"China","phone":"5681693543"},
{"id":10,"first_name":"Keir","last_name":"Grumble","email":"kgrumble9@nifty.com","date_of_birth":"9/15/1995","age":27,"country":"Peru","phone":"2567767660"},
{"id":11,"first_name":"Jesselyn","last_name":"Trent","email":"jtrenta@techcrunch.com","date_of_birth":"12/21/1996","age":49,"country":"Philippines","phone":"1832455326"},
{"id":12,"first_name":"Robinetta","last_name":"Iglesia","email":"riglesiab@cpanel.net","date_of_birth":"6/29/1982","age":24,"country":"Czech Republic","phone":"6869895678"},
{"id":13,"first_name":"Allyn","last_name":"Thrustle","email":"athrustlec@state.tx.us","date_of_birth":"11/20/1974","age":54,"country":"Colombia","phone":"1579185809"},
{"id":14,"first_name":"Anabal","last_name":"Biddles","email":"abiddlesd@nydailynews.com","date_of_birth":"8/29/1977","age":34,"country":"Czech Republic","phone":"5776565460"},
{"id":15,"first_name":"Blithe","last_name":"Huyhton","email":"bhuyhtone@buzzfeed.com","date_of_birth":"11/26/2009","age":42,"country":"Ukraine","phone":"9046104515"},
{"id":16,"first_name":"Wendel","last_name":"Olander","email":"wolanderf@whitehouse.gov","date_of_birth":"12/18/2000","age":46,"country":"Indonesia","phone":"7896044716"},
{"id":17,"first_name":"Gib","last_name":"Rounce","email":"grounceg@sciencedirect.com","date_of_birth":"2/11/2018","age":57,"country":"Indonesia","phone":"6466388722"},
{"id":18,"first_name":"Lauralee","last_name":"Frizzell","email":"lfrizzellh@canalblog.com","date_of_birth":"7/5/1982","age":50,"country":"Bolivia","phone":"8834581584"},
{"id":19,"first_name":"Odetta","last_name":"Kyteley","email":"okyteleyi@bloglines.com","date_of_birth":"1/5/1979","age":29,"country":"Philippines","phone":"5378893862"},
{"id":20,"first_name":"Dennison","last_name":"Clougher","email":"dclougherj@w3.org","date_of_birth":"5/1/1989","age":27,"country":"Portugal","phone":"9502949804"},
{"id":21,"first_name":"Sampson","last_name":"Darwood","email":"sdarwoodk@sina.com.cn","date_of_birth":"7/18/2016","age":31,"country":"Bosnia and Herzegovina","phone":"4033430748"},
{"id":22,"first_name":"Rusty","last_name":"Skatcher","email":"rskatcherl@latimes.com","date_of_birth":"1/3/1984","age":44,"country":"Indonesia","phone":"2928488603"},
{"id":23,"first_name":"Si","last_name":"Glandfield","email":"sglandfieldm@examiner.com","date_of_birth":"11/28/1992","age":55,"country":"Sweden","phone":"3862753621"},
{"id":24,"first_name":"Abeu","last_name":"Von Welldun","email":"avonwelldunn@weebly.com","date_of_birth":"4/13/2009","age":32,"country":"Slovenia","phone":"4869735327"},
{"id":25,"first_name":"Millicent","last_name":"Hows","email":"mhowso@istockphoto.com","date_of_birth":"6/25/2016","age":33,"country":"Belarus","phone":"3866292904"},
{"id":26,"first_name":"Lizette","last_name":"Adamik","email":"ladamikp@youtube.com","date_of_birth":"4/10/2014","age":54,"country":"China","phone":"4996785451"},
{"id":27,"first_name":"Ardelis","last_name":"O'Fielly","email":"aofiellyq@yellowpages.com","date_of_birth":"12/4/1973","age":36,"country":"Zambia","phone":"8479439640"},
{"id":28,"first_name":"Maury","last_name":"Vayro","email":"mvayror@loc.gov","date_of_birth":"11/12/1977","age":48,"country":"Russia","phone":"1531030538"},
{"id":29,"first_name":"Helen","last_name":"Blase","email":"hblases@home.pl","date_of_birth":"6/1/2009","age":19,"country":"Czech Republic","phone":"6205947062"},
{"id":30,"first_name":"Mildred","last_name":"Caskey","email":"mcaskeyt@hc360.com","date_of_birth":"7/26/2003","age":46,"country":"France","phone":"2721333633"},
{"id":31,"first_name":"Yank","last_name":"Jentges","email":"yjentgesu@ow.ly","date_of_birth":"2/20/2016","age":22,"country":"Sweden","phone":"6786975122"},
{"id":32,"first_name":"Ericha","last_name":"Dewire","email":"edewirev@github.com","date_of_birth":"10/4/2006","age":27,"country":"Philippines","phone":"4841967250"},
{"id":33,"first_name":"Georgiana","last_name":"Timmes","email":"gtimmesw@skyrock.com","date_of_birth":"5/6/1981","age":56,"country":"Ukraine","phone":"9761007976"},
{"id":34,"first_name":"Mandie","last_name":"Widd","email":"mwiddx@jugem.jp","date_of_birth":"4/8/2012","age":29,"country":"Angola","phone":"2033863073"},
{"id":35,"first_name":"Florenza","last_name":"Boyson","email":"fboysony@java.com","date_of_birth":"12/20/1983","age":56,"country":"Russia","phone":"4133916870"},
{"id":36,"first_name":"Brant","last_name":"Mughal","email":"bmughalz@blinklist.com","date_of_birth":"11/18/2001","age":42,"country":"Israel","phone":"7794136084"},
{"id":37,"first_name":"Asher","last_name":"Reggiani","email":"areggiani10@youku.com","date_of_birth":"1/29/2018","age":27,"country":"Philippines","phone":"2266180844"},
{"id":38,"first_name":"Karissa","last_name":"Scaife","email":"kscaife11@scribd.com","date_of_birth":"12/9/1989","age":25,"country":"China","phone":"6402839090"},
{"id":39,"first_name":"Timoteo","last_name":"Stut","email":"tstut12@angelfire.com","date_of_birth":"2/10/1975","age":56,"country":"Indonesia","phone":"5113555620"},
{"id":40,"first_name":"Hertha","last_name":"Joynt","email":"hjoynt13@yandex.ru","date_of_birth":"9/27/1987","age":45,"country":"Greece","phone":"5905269976"},
{"id":41,"first_name":"Aldin","last_name":"Maliphant","email":"amaliphant14@twitpic.com","date_of_birth":"12/12/1996","age":40,"country":"Portugal","phone":"4925286449"},
{"id":42,"first_name":"Lilli","last_name":"Gilfoyle","email":"lgilfoyle15@yahoo.com","date_of_birth":"2/26/1977","age":52,"country":"Brazil","phone":"1279717209"},
{"id":43,"first_name":"Hamilton","last_name":"Bramich","email":"hbramich16@surveymonkey.com","date_of_birth":"1/20/1982","age":45,"country":"Morocco","phone":"5654873724"},
{"id":44,"first_name":"Kesley","last_name":"Cavill","email":"kcavill17@netlog.com","date_of_birth":"5/18/2019","age":29,"country":"Czech Republic","phone":"2585032447"},
{"id":45,"first_name":"Lurline","last_name":"Noweak","email":"lnoweak18@seesaa.net","date_of_birth":"7/29/1980","age":20,"country":"France","phone":"2173792902"},
{"id":46,"first_name":"Minnie","last_name":"Murra","email":"mmurra19@typepad.com","date_of_birth":"6/10/1980","age":51,"country":"Indonesia","phone":"6234587752"},
{"id":47,"first_name":"Yuri","last_name":"Vickarman","email":"yvickarman1a@parallels.com","date_of_birth":"3/29/1973","age":28,"country":"China","phone":"3621284833"},
{"id":48,"first_name":"Kelly","last_name":"Navan","email":"knavan1b@who.int","date_of_birth":"5/28/1980","age":52,"country":"Azerbaijan","phone":"6568002023"},
{"id":49,"first_name":"Pegeen","last_name":"Dracey","email":"pdracey1c@wikia.com","date_of_birth":"1/23/1983","age":57,"country":"China","phone":"8721798466"},
{"id":50,"first_name":"Zorah","last_name":"Gallemore","email":"zgallemore1d@wordpress.com","date_of_birth":"8/22/2008","age":33,"country":"Indonesia","phone":"4851199850"},
{"id":51,"first_name":"Codie","last_name":"Keeves","email":"ckeeves1e@soundcloud.com","date_of_birth":"9/10/1970","age":34,"country":"Russia","phone":"7171028036"},
{"id":52,"first_name":"Olenka","last_name":"Kidby","email":"okidby1f@rambler.ru","date_of_birth":"1/3/1976","age":50,"country":"New Zealand","phone":"6236127788"},
{"id":53,"first_name":"Alix","last_name":"Kopacek","email":"akopacek1g@miibeian.gov.cn","date_of_birth":"9/20/2019","age":38,"country":"Czech Republic","phone":"9893812172"},
{"id":54,"first_name":"Feliks","last_name":"Goodwell","email":"fgoodwell1h@scribd.com","date_of_birth":"11/1/2015","age":21,"country":"Philippines","phone":"1857624398"},
{"id":55,"first_name":"Joelie","last_name":"Georgot","email":"jgeorgot1i@blog.com","date_of_birth":"10/10/1978","age":41,"country":"Greece","phone":"5459609883"},
{"id":56,"first_name":"Tobi","last_name":"Riddel","email":"triddel1j@noaa.gov","date_of_birth":"12/8/1997","age":28,"country":"Brazil","phone":"5804476698"},
{"id":57,"first_name":"Sayer","last_name":"Casebourne","email":"scasebourne1k@yale.edu","date_of_birth":"11/28/1983","age":31,"country":"China","phone":"7214559822"},
{"id":58,"first_name":"Armin","last_name":"Blofield","email":"ablofield1l@friendfeed.com","date_of_birth":"1/1/1971","age":46,"country":"Greece","phone":"2831550979"},
{"id":59,"first_name":"Marlin","last_name":"McComiskey","email":"mmccomiskey1m@alibaba.com","date_of_birth":"2/20/1973","age":33,"country":"China","phone":"1102136866"},
{"id":60,"first_name":"Jard","last_name":"Kasparski","email":"jkasparski1n@uiuc.edu","date_of_birth":"5/30/2014","age":51,"country":"Indonesia","phone":"9181284306"},
{"id":61,"first_name":"Elane","last_name":"Hutcheon","email":"ehutcheon1o@addthis.com","date_of_birth":"5/4/2013","age":49,"country":"China","phone":"4497194175"},
{"id":62,"first_name":"Audre","last_name":"Humphris","email":"ahumphris1p@europa.eu","date_of_birth":"3/6/1996","age":34,"country":"China","phone":"7501415858"},
{"id":63,"first_name":"Merv","last_name":"Shellshear","email":"mshellshear1q@ow.ly","date_of_birth":"5/16/1996","age":46,"country":"Brazil","phone":"7045560663"},
{"id":64,"first_name":"Quinn","last_name":"Neild","email":"qneild1r@surveymonkey.com","date_of_birth":"7/21/1990","age":24,"country":"China","phone":"7548382018"},
{"id":65,"first_name":"Maurits","last_name":"Davydoch","email":"mdavydoch1s@thetimes.co.uk","date_of_birth":"8/12/1972","age":44,"country":"China","phone":"9542511210"},
{"id":66,"first_name":"Ab","last_name":"Scud","email":"ascud1t@cornell.edu","date_of_birth":"5/30/2019","age":51,"country":"Russia","phone":"3433860050"},
{"id":67,"first_name":"Noach","last_name":"Ransom","email":"nransom1u@buzzfeed.com","date_of_birth":"4/30/1978","age":37,"country":"United Kingdom","phone":"1611101848"},
{"id":68,"first_name":"Ortensia","last_name":"Scanterbury","email":"oscanterbury1v@zimbio.com","date_of_birth":"2/26/1999","age":52,"country":"Ukraine","phone":"2061262689"},
{"id":69,"first_name":"Robbie","last_name":"Pachmann","email":"rpachmann1w@bing.com","date_of_birth":"7/24/1971","age":42,"country":"Uganda","phone":"5467185225"},
{"id":70,"first_name":"Karole","last_name":"Loachhead","email":"kloachhead1x@omniture.com","date_of_birth":"12/21/1993","age":52,"country":"Croatia","phone":"8946070623"},
{"id":71,"first_name":"Aileen","last_name":"Hakking","email":"ahakking1y@cbsnews.com","date_of_birth":"9/7/2017","age":24,"country":"Brazil","phone":"8782068721"},
{"id":72,"first_name":"Reube","last_name":"Poppy","email":"rpoppy1z@google.com","date_of_birth":"7/7/1991","age":28,"country":"Argentina","phone":"2906152837"},
{"id":73,"first_name":"Rivkah","last_name":"Ghelardoni","email":"rghelardoni20@vkontakte.ru","date_of_birth":"12/9/2006","age":47,"country":"Lebanon","phone":"8567460523"},
{"id":74,"first_name":"Suzie","last_name":"Hagergham","email":"shagergham21@macromedia.com","date_of_birth":"5/19/2010","age":26,"country":"United States","phone":"9367155545"},
{"id":75,"first_name":"Brear","last_name":"Breche","email":"bbreche22@mapquest.com","date_of_birth":"8/25/1990","age":31,"country":"Russia","phone":"3669726681"},
{"id":76,"first_name":"Kizzee","last_name":"Fausch","email":"kfausch23@digg.com","date_of_birth":"9/26/1993","age":27,"country":"France","phone":"4216301690"},
{"id":77,"first_name":"Jessa","last_name":"Weaben","email":"jweaben24@chicagotribune.com","date_of_birth":"8/13/2005","age":53,"country":"Russia","phone":"1268234223"},
{"id":78,"first_name":"Winthrop","last_name":"Beadman","email":"wbeadman25@theatlantic.com","date_of_birth":"7/14/1987","age":39,"country":"United States","phone":"2023051828"},
{"id":79,"first_name":"Sean","last_name":"Levin","email":"slevin26@eepurl.com","date_of_birth":"1/9/1998","age":42,"country":"Ukraine","phone":"4861017777"},
{"id":80,"first_name":"Sherye","last_name":"Spadaro","email":"sspadaro27@ustream.tv","date_of_birth":"10/26/1973","age":43,"country":"China","phone":"6421308545"},
{"id":81,"first_name":"Marilyn","last_name":"Parlor","email":"mparlor28@apache.org","date_of_birth":"5/9/2000","age":43,"country":"Sweden","phone":"3438243002"},
{"id":82,"first_name":"Zerk","last_name":"Menear","email":"zmenear29@t.co","date_of_birth":"4/3/1982","age":44,"country":"Bolivia","phone":"4405103205"},
{"id":83,"first_name":"Massimo","last_name":"Schutter","email":"mschutter2a@spotify.com","date_of_birth":"5/26/2002","age":20,"country":"Malaysia","phone":"2508185891"},
{"id":84,"first_name":"Matthaeus","last_name":"McGray","email":"mmcgray2b@time.com","date_of_birth":"2/22/1988","age":56,"country":"Tunisia","phone":"5083538984"},
{"id":85,"first_name":"Reinaldos","last_name":"Kaygill","email":"rkaygill2c@phpbb.com","date_of_birth":"1/15/2014","age":45,"country":"Cyprus","phone":"4377642789"},
{"id":86,"first_name":"Novelia","last_name":"Boatman","email":"nboatman2d@lulu.com","date_of_birth":"1/10/1986","age":22,"country":"Indonesia","phone":"3546284955"},
{"id":87,"first_name":"Bailey","last_name":"Crother","email":"bcrother2e@hatena.ne.jp","date_of_birth":"4/13/2000","age":33,"country":"Russia","phone":"9662153488"},
{"id":88,"first_name":"Jacquelynn","last_name":"Horick","email":"jhorick2f@instagram.com","date_of_birth":"2/14/2000","age":51,"country":"China","phone":"8161351885"},
{"id":89,"first_name":"Kary","last_name":"McCloud","email":"kmccloud2g@eepurl.com","date_of_birth":"3/29/2003","age":58,"country":"United Kingdom","phone":"2101512380"},
{"id":90,"first_name":"Ailee","last_name":"Sever","email":"asever2h@telegraph.co.uk","date_of_birth":"11/12/1992","age":28,"country":"China","phone":"9082951619"},
{"id":91,"first_name":"Damian","last_name":"Brayn","email":"dbrayn2i@amazonaws.com","date_of_birth":"1/11/1978","age":52,"country":"Indonesia","phone":"3294840962"},
{"id":92,"first_name":"Carlye","last_name":"Westwood","email":"cwestwood2j@walmart.com","date_of_birth":"2/29/2000","age":51,"country":"Nigeria","phone":"7511032819"},
{"id":93,"first_name":"Hendrick","last_name":"Piatti","email":"hpiatti2k@ucoz.ru","date_of_birth":"6/24/1977","age":52,"country":"France","phone":"8977278167"},
{"id":94,"first_name":"Grayce","last_name":"O'Suaird","email":"gosuaird2l@over-blog.com","date_of_birth":"11/9/1976","age":36,"country":"Indonesia","phone":"5043158567"},
{"id":95,"first_name":"Nadean","last_name":"Footer","email":"nfooter2m@cdbaby.com","date_of_birth":"3/4/2009","age":40,"country":"Indonesia","phone":"7287857973"},
{"id":96,"first_name":"Helyn","last_name":"Chafer","email":"hchafer2n@google.de","date_of_birth":"6/11/2019","age":41,"country":"Philippines","phone":"5307003016"},
{"id":97,"first_name":"Aurthur","last_name":"Beaushaw","email":"abeaushaw2o@gizmodo.com","date_of_birth":"10/5/1983","age":51,"country":"China","phone":"8595511710"},
{"id":98,"first_name":"Henryetta","last_name":"Degue","email":"hdegue2p@cam.ac.uk","date_of_birth":"2/11/1987","age":44,"country":"Sri Lanka","phone":"3506328317"},
{"id":99,"first_name":"Richardo","last_name":"Leere","email":"rleere2q@360.cn","date_of_birth":"12/30/2000","age":24,"country":"China","phone":"5068099777"},
{"id":100,"first_name":"Yul","last_name":"Trusslove","email":"ytrusslove2r@dagondesign.com","date_of_birth":"6/14/1989","age":21,"country":"El Salvador","phone":"8007798600"},
{"id":101,"first_name":"Janette","last_name":"Brunone","email":"jbrunone2s@ow.ly","date_of_birth":"3/16/1977","age":38,"country":"Burkina Faso","phone":"2338597128"},
{"id":102,"first_name":"Mavra","last_name":"Stoven","email":"mstoven2t@infoseek.co.jp","date_of_birth":"4/9/2015","age":46,"country":"Russia","phone":"5379254730"},
{"id":103,"first_name":"Ermanno","last_name":"Wickersley","email":"ewickersley2u@spiegel.de","date_of_birth":"3/28/1990","age":50,"country":"Czech Republic","phone":"2418114099"},
{"id":104,"first_name":"Raina","last_name":"Chellingworth","email":"rchellingworth2v@discuz.net","date_of_birth":"12/1/2012","age":27,"country":"Indonesia","phone":"9964949497"},
{"id":105,"first_name":"Ricki","last_name":"McGlue","email":"rmcglue2w@yandex.ru","date_of_birth":"1/22/1998","age":36,"country":"Armenia","phone":"8217881175"},
{"id":106,"first_name":"Heindrick","last_name":"Czajkowski","email":"hczajkowski2x@simplemachines.org","date_of_birth":"9/20/1988","age":48,"country":"Russia","phone":"7422175312"},
{"id":107,"first_name":"Carlen","last_name":"Tinsey","email":"ctinsey2y@statcounter.com","date_of_birth":"9/4/2012","age":25,"country":"China","phone":"9523098752"},
{"id":108,"first_name":"Andonis","last_name":"Tottie","email":"atottie2z@seesaa.net","date_of_birth":"7/6/1977","age":24,"country":"Ukraine","phone":"4908298795"},
{"id":109,"first_name":"Maribel","last_name":"Jukes","email":"mjukes30@meetup.com","date_of_birth":"4/10/2007","age":36,"country":"United States","phone":"6501185257"},
{"id":110,"first_name":"Valma","last_name":"Bortolussi","email":"vbortolussi31@mapy.cz","date_of_birth":"1/15/1984","age":41,"country":"Sweden","phone":"9462717643"},
{"id":111,"first_name":"Reggie","last_name":"Hold","email":"rhold32@msu.edu","date_of_birth":"3/6/1990","age":29,"country":"Finland","phone":"1697063491"},
{"id":112,"first_name":"Rozella","last_name":"Cornelius","email":"rcornelius33@ebay.co.uk","date_of_birth":"11/17/2003","age":44,"country":"China","phone":"4866365273"},
{"id":113,"first_name":"Dorian","last_name":"Schiersch","email":"dschiersch34@bloomberg.com","date_of_birth":"5/27/1972","age":39,"country":"New Zealand","phone":"2832094316"},
{"id":114,"first_name":"Zahara","last_name":"Turmall","email":"zturmall35@macromedia.com","date_of_birth":"10/19/2003","age":53,"country":"Serbia","phone":"1313053658"},
{"id":115,"first_name":"Nanette","last_name":"Westmoreland","email":"nwestmoreland36@artisteer.com","date_of_birth":"4/25/2004","age":37,"country":"China","phone":"9263295456"},
{"id":116,"first_name":"Katha","last_name":"Kerrey","email":"kkerrey37@admin.ch","date_of_birth":"9/10/1986","age":47,"country":"Philippines","phone":"9241902341"},
{"id":117,"first_name":"Lusa","last_name":"Bransden","email":"lbransden38@pcworld.com","date_of_birth":"7/15/1976","age":53,"country":"Finland","phone":"2459512747"},
{"id":118,"first_name":"Hetti","last_name":"Fidilis","email":"hfidilis39@dailymotion.com","date_of_birth":"11/30/2015","age":40,"country":"Poland","phone":"9511969967"},
{"id":119,"first_name":"Morganne","last_name":"Bedburrow","email":"mbedburrow3a@baidu.com","date_of_birth":"4/11/1984","age":21,"country":"Zimbabwe","phone":"4566132572"},
{"id":120,"first_name":"Neil","last_name":"Backe","email":"nbacke3b@apache.org","date_of_birth":"10/25/2010","age":56,"country":"Czech Republic","phone":"4275684950"},
{"id":121,"first_name":"Jareb","last_name":"Hastilow","email":"jhastilow3c@mtv.com","date_of_birth":"8/5/1991","age":21,"country":"Brazil","phone":"8644694507"},
{"id":122,"first_name":"Robinet","last_name":"Zavattero","email":"rzavattero3d@arizona.edu","date_of_birth":"8/10/1984","age":54,"country":"Canada","phone":"5593251347"},
{"id":123,"first_name":"Evangelina","last_name":"Bremmell","email":"ebremmell3e@weibo.com","date_of_birth":"4/11/2011","age":20,"country":"Sweden","phone":"2255642405"},
{"id":124,"first_name":"Bess","last_name":"Strass","email":"bstrass3f@hao123.com","date_of_birth":"10/9/1970","age":39,"country":"Poland","phone":"1332386622"},
{"id":125,"first_name":"Ag","last_name":"D'eye","email":"adeye3g@etsy.com","date_of_birth":"12/13/2018","age":41,"country":"Israel","phone":"4771308405"},
{"id":126,"first_name":"Laverna","last_name":"Farndale","email":"lfarndale3h@yolasite.com","date_of_birth":"4/28/1973","age":21,"country":"China","phone":"3271092631"},
{"id":127,"first_name":"Darrelle","last_name":"Karolowski","email":"dkarolowski3i@sohu.com","date_of_birth":"9/11/1993","age":19,"country":"Indonesia","phone":"8147720744"},
{"id":128,"first_name":"Felizio","last_name":"Howard - Gater","email":"fhowardgater3j@ebay.co.uk","date_of_birth":"8/16/2006","age":55,"country":"Brazil","phone":"8491842087"},
{"id":129,"first_name":"Waiter","last_name":"McTrustrie","email":"wmctrustrie3k@bigcartel.com","date_of_birth":"9/27/1977","age":48,"country":"United States","phone":"6509641417"},
{"id":130,"first_name":"Imelda","last_name":"Wakeman","email":"iwakeman3l@infoseek.co.jp","date_of_birth":"7/7/2007","age":32,"country":"Indonesia","phone":"2706280100"},
{"id":131,"first_name":"Nicolais","last_name":"Collet","email":"ncollet3m@amazonaws.com","date_of_birth":"5/3/2006","age":35,"country":"Indonesia","phone":"1994953111"},
{"id":132,"first_name":"Kelci","last_name":"Mapham","email":"kmapham3n@typepad.com","date_of_birth":"12/25/1975","age":23,"country":"Belarus","phone":"1859431172"},
{"id":133,"first_name":"Caren","last_name":"Duckworth","email":"cduckworth3o@java.com","date_of_birth":"10/27/1981","age":42,"country":"China","phone":"3562359229"},
{"id":134,"first_name":"Hammad","last_name":"Vennart","email":"hvennart3p@bloglines.com","date_of_birth":"7/29/1976","age":51,"country":"Canada","phone":"3016330145"},
{"id":135,"first_name":"Eustacia","last_name":"Smitten","email":"esmitten3q@virginia.edu","date_of_birth":"8/28/2013","age":33,"country":"Philippines","phone":"1471190517"},
{"id":136,"first_name":"Henriette","last_name":"Dunton","email":"hdunton3r@angelfire.com","date_of_birth":"1/3/2014","age":57,"country":"Ukraine","phone":"8257490302"},
{"id":137,"first_name":"Boyd","last_name":"Bover","email":"bbover3s@qq.com","date_of_birth":"2/17/2012","age":20,"country":"Russia","phone":"8473855372"},
{"id":138,"first_name":"Marybeth","last_name":"Genever","email":"mgenever3t@ted.com","date_of_birth":"3/19/1985","age":25,"country":"Argentina","phone":"9008035935"},
{"id":139,"first_name":"Karel","last_name":"Chark","email":"kchark3u@123-reg.co.uk","date_of_birth":"10/23/2003","age":37,"country":"China","phone":"8273262214"},
{"id":140,"first_name":"Annecorinne","last_name":"Tummons","email":"atummons3v@sciencedirect.com","date_of_birth":"12/25/2011","age":20,"country":"Yemen","phone":"7015210550"},
{"id":141,"first_name":"Hillier","last_name":"Lumly","email":"hlumly3w@jimdo.com","date_of_birth":"12/24/1973","age":21,"country":"Sweden","phone":"4674906628"},
{"id":142,"first_name":"Florri","last_name":"Gronaller","email":"fgronaller3x@bloglovin.com","date_of_birth":"7/28/2004","age":42,"country":"Madagascar","phone":"2767922762"},
{"id":143,"first_name":"Nevin","last_name":"Lampke","email":"nlampke3y@whitehouse.gov","date_of_birth":"3/18/2007","age":25,"country":"China","phone":"5512647149"},
{"id":144,"first_name":"Penelopa","last_name":"Chatan","email":"pchatan3z@howstuffworks.com","date_of_birth":"5/24/1996","age":47,"country":"Portugal","phone":"7194371256"},
{"id":145,"first_name":"Desdemona","last_name":"Petrillo","email":"dpetrillo40@mit.edu","date_of_birth":"2/15/1980","age":53,"country":"China","phone":"8338648572"},
{"id":146,"first_name":"Jimmy","last_name":"Piddlehinton","email":"jpiddlehinton41@umich.edu","date_of_birth":"11/5/1993","age":58,"country":"Canada","phone":"1938695969"},
{"id":147,"first_name":"Roseann","last_name":"McKelvey","email":"rmckelvey42@buzzfeed.com","date_of_birth":"4/24/2007","age":44,"country":"Malaysia","phone":"6186582286"},
{"id":148,"first_name":"Damien","last_name":"Petruszka","email":"dpetruszka43@opensource.org","date_of_birth":"9/3/2015","age":19,"country":"Netherlands","phone":"5527107116"},
{"id":149,"first_name":"Elsy","last_name":"Bellefonte","email":"ebellefonte44@studiopress.com","date_of_birth":"4/21/2017","age":24,"country":"Russia","phone":"8933095740"},
{"id":150,"first_name":"Berty","last_name":"Widdowfield","email":"bwiddowfield45@posterous.com","date_of_birth":"9/16/1984","age":49,"country":"Niger","phone":"2214647003"},
{"id":151,"first_name":"Laverna","last_name":"Marking","email":"lmarking46@who.int","date_of_birth":"7/21/2016","age":30,"country":"Portugal","phone":"1565826086"},
{"id":152,"first_name":"Magda","last_name":"Weyman","email":"mweyman47@a8.net","date_of_birth":"9/14/2007","age":47,"country":"Russia","phone":"3562707917"},
{"id":153,"first_name":"Aviva","last_name":"Janota","email":"ajanota48@gravatar.com","date_of_birth":"11/21/2000","age":44,"country":"Portugal","phone":"4677974307"},
{"id":154,"first_name":"Timmi","last_name":"La Padula","email":"tlapadula49@fastcompany.com","date_of_birth":"12/13/2005","age":54,"country":"Russia","phone":"4502162220"},
{"id":155,"first_name":"Karena","last_name":"Tobias","email":"ktobias4a@multiply.com","date_of_birth":"8/8/2008","age":18,"country":"China","phone":"2992868867"},
{"id":156,"first_name":"Leonard","last_name":"Roux","email":"lroux4b@foxnews.com","date_of_birth":"8/29/1971","age":22,"country":"Brazil","phone":"6125788739"},
{"id":157,"first_name":"Lira","last_name":"Thunnerclef","email":"lthunnerclef4c@bloglovin.com","date_of_birth":"11/28/2011","age":18,"country":"Indonesia","phone":"6145653700"},
{"id":158,"first_name":"Sandy","last_name":"Pedycan","email":"spedycan4d@si.edu","date_of_birth":"3/26/2006","age":28,"country":"Japan","phone":"8688476979"},
{"id":159,"first_name":"Clywd","last_name":"Wabersich","email":"cwabersich4e@odnoklassniki.ru","date_of_birth":"9/7/2018","age":20,"country":"Portugal","phone":"2276852410"},
{"id":160,"first_name":"Courtenay","last_name":"Alston","email":"calston4f@bluehost.com","date_of_birth":"7/27/2012","age":19,"country":"China","phone":"1184749827"},
{"id":161,"first_name":"Beulah","last_name":"Cozzi","email":"bcozzi4g@nymag.com","date_of_birth":"3/8/2018","age":24,"country":"Indonesia","phone":"6823226030"},
{"id":162,"first_name":"Jemimah","last_name":"Cubbini","email":"jcubbini4h@buzzfeed.com","date_of_birth":"12/24/1999","age":20,"country":"Portugal","phone":"5548979542"},
{"id":163,"first_name":"Gardiner","last_name":"Mellsop","email":"gmellsop4i@moonfruit.com","date_of_birth":"10/7/1978","age":55,"country":"China","phone":"7653879569"},
{"id":164,"first_name":"Ericha","last_name":"Haggath","email":"ehaggath4j@google.com.au","date_of_birth":"10/26/1985","age":56,"country":"United States","phone":"3048243260"},
{"id":165,"first_name":"Merrick","last_name":"Yousef","email":"myousef4k@china.com.cn","date_of_birth":"3/1/2002","age":25,"country":"France","phone":"4089957693"},
{"id":166,"first_name":"Gwenora","last_name":"Legerton","email":"glegerton4l@weebly.com","date_of_birth":"11/18/2000","age":20,"country":"Portugal","phone":"2598389063"},
{"id":167,"first_name":"Mollie","last_name":"Brotherhed","email":"mbrotherhed4m@salon.com","date_of_birth":"7/20/1991","age":49,"country":"China","phone":"7519737250"},
{"id":168,"first_name":"Editha","last_name":"Filyukov","email":"efilyukov4n@altervista.org","date_of_birth":"7/1/2018","age":51,"country":"Indonesia","phone":"9042466093"},
{"id":169,"first_name":"Charlie","last_name":"Kenwood","email":"ckenwood4o@sun.com","date_of_birth":"4/7/1998","age":57,"country":"Indonesia","phone":"1896857869"},
{"id":170,"first_name":"Teddi","last_name":"Tompkinson","email":"ttompkinson4p@ucoz.ru","date_of_birth":"6/27/2006","age":48,"country":"Japan","phone":"5518074297"},
{"id":171,"first_name":"Aleen","last_name":"Paniman","email":"apaniman4q@eepurl.com","date_of_birth":"11/23/2014","age":25,"country":"Mali","phone":"6764491248"},
{"id":172,"first_name":"Reynolds","last_name":"Brenston","email":"rbrenston4r@dailymail.co.uk","date_of_birth":"12/1/2009","age":49,"country":"Russia","phone":"4974343446"},
{"id":173,"first_name":"Chrisy","last_name":"Flaverty","email":"cflaverty4s@arstechnica.com","date_of_birth":"2/17/1995","age":46,"country":"Turkmenistan","phone":"6138338390"},
{"id":174,"first_name":"Sebastiano","last_name":"Danis","email":"sdanis4t@google.it","date_of_birth":"5/10/2009","age":29,"country":"Philippines","phone":"8779013511"},
{"id":175,"first_name":"Elyssa","last_name":"Breslin","email":"ebreslin4u@facebook.com","date_of_birth":"1/26/1986","age":44,"country":"Mexico","phone":"6136432633"},
{"id":176,"first_name":"Milena","last_name":"Ludgate","email":"mludgate4v@tmall.com","date_of_birth":"3/18/1995","age":29,"country":"China","phone":"3813070933"},
{"id":177,"first_name":"Witty","last_name":"Iacovaccio","email":"wiacovaccio4w@zdnet.com","date_of_birth":"12/15/2016","age":45,"country":"Latvia","phone":"4286451382"},
{"id":178,"first_name":"Gregoor","last_name":"Lukacs","email":"glukacs4x@umn.edu","date_of_birth":"2/13/1997","age":28,"country":"Tajikistan","phone":"2608895902"},
{"id":179,"first_name":"Nannette","last_name":"Linne","email":"nlinne4y@simplemachines.org","date_of_birth":"8/12/1998","age":54,"country":"Portugal","phone":"9223258369"},
{"id":180,"first_name":"Elspeth","last_name":"Biddlecombe","email":"ebiddlecombe4z@mit.edu","date_of_birth":"12/21/2018","age":29,"country":"China","phone":"1756954420"},
{"id":181,"first_name":"Thalia","last_name":"Mogie","email":"tmogie50@1und1.de","date_of_birth":"4/13/1990","age":58,"country":"Indonesia","phone":"9724211355"},
{"id":182,"first_name":"Charlotta","last_name":"Palatino","email":"cpalatino51@bigcartel.com","date_of_birth":"11/2/2012","age":52,"country":"Azerbaijan","phone":"5638712604"},
{"id":183,"first_name":"Delcina","last_name":"Dohrmann","email":"ddohrmann52@marriott.com","date_of_birth":"12/16/1999","age":19,"country":"Philippines","phone":"5441999566"},
{"id":184,"first_name":"Evy","last_name":"Ropkes","email":"eropkes53@smh.com.au","date_of_birth":"9/5/1999","age":49,"country":"China","phone":"4421854048"},
{"id":185,"first_name":"Dwight","last_name":"Kiellor","email":"dkiellor54@reference.com","date_of_birth":"8/6/2002","age":45,"country":"France","phone":"3974888815"},
{"id":186,"first_name":"Saraann","last_name":"Muddicliffe","email":"smuddicliffe55@sbwire.com","date_of_birth":"4/7/1993","age":25,"country":"Japan","phone":"2381783208"},
{"id":187,"first_name":"Conant","last_name":"Kedge","email":"ckedge56@nba.com","date_of_birth":"6/14/1986","age":26,"country":"Guyana","phone":"2072566913"},
{"id":188,"first_name":"Cathlene","last_name":"Razzell","email":"crazzell57@mapy.cz","date_of_birth":"3/3/2017","age":58,"country":"Sudan","phone":"2647899334"},
{"id":189,"first_name":"Sammie","last_name":"Kitchenman","email":"skitchenman58@google.ca","date_of_birth":"11/14/2007","age":57,"country":"Indonesia","phone":"5688599729"},
{"id":190,"first_name":"Godfry","last_name":"Bury","email":"gbury59@nifty.com","date_of_birth":"6/24/2005","age":36,"country":"Sweden","phone":"4462828286"},
{"id":191,"first_name":"Drew","last_name":"Baroc","email":"dbaroc5a@auda.org.au","date_of_birth":"9/21/2007","age":36,"country":"Peru","phone":"3687342285"},
{"id":192,"first_name":"Nollie","last_name":"Madeley","email":"nmadeley5b@sina.com.cn","date_of_birth":"5/30/1999","age":56,"country":"China","phone":"7809602626"},
{"id":193,"first_name":"Cornell","last_name":"Godfrey","email":"cgodfrey5c@ted.com","date_of_birth":"2/15/1972","age":41,"country":"Russia","phone":"2363017764"},
{"id":194,"first_name":"Sigfried","last_name":"Manuello","email":"smanuello5d@merriam-webster.com","date_of_birth":"12/23/1985","age":21,"country":"Argentina","phone":"9815658460"},
{"id":195,"first_name":"Desi","last_name":"Leppard","email":"dleppard5e@umich.edu","date_of_birth":"2/5/2013","age":53,"country":"Indonesia","phone":"7288761010"},
{"id":196,"first_name":"Maddalena","last_name":"Pierucci","email":"mpierucci5f@hao123.com","date_of_birth":"6/20/1974","age":24,"country":"Madagascar","phone":"9042365606"},
{"id":197,"first_name":"Temp","last_name":"Stroobant","email":"tstroobant5g@surveymonkey.com","date_of_birth":"9/23/1984","age":41,"country":"Armenia","phone":"8432355059"},
{"id":198,"first_name":"Rem","last_name":"Necrews","email":"rnecrews5h@miibeian.gov.cn","date_of_birth":"6/24/1992","age":43,"country":"Philippines","phone":"2767124904"},
{"id":199,"first_name":"Dorey","last_name":"Massenhove","email":"dmassenhove5i@hatena.ne.jp","date_of_birth":"3/25/2004","age":55,"country":"Poland","phone":"6214532860"},
{"id":200,"first_name":"Ora","last_name":"Leyrroyd","email":"oleyrroyd5j@ted.com","date_of_birth":"6/23/1995","age":23,"country":"Brazil","phone":"5127116409"}]